mt19937ar/__init__.py
mt19937ar/mt19937ar.py
mt19937ar/py.typed
mt19937ar-0.1.2.dist-info/METADATA
mt19937ar-0.1.2.dist-info/WHEEL
mt19937ar-0.1.2.dist-info/licenses/LICENSE
mt19937ar-0.1.2.dist-info/RECORD
