Metadata-Version: 2.3
Name: mt19937ar
Version: 0.1.2
Summary: mt19937ar for Python
Project-URL: Homepage, https://github.com/zurukumo/mt19937ar
Project-URL: Issues, https://github.com/zurukumo/mt19937ar/issues
Author-email: zurukumo <zurukumo@gmail.com>
Classifier: Intended Audience :: Developers
Classifier: License :: OSI Approved :: MIT License
Classifier: Operating System :: OS Independent
Classifier: Programming Language :: Python :: 3
Classifier: Programming Language :: Python :: 3.10
Classifier: Programming Language :: Python :: 3.11
Classifier: Programming Language :: Python :: 3.12
Classifier: Programming Language :: Python :: 3.13
Requires-Python: >=3.10
